{
  "commit": "815dd4ece678e9823c89eaaf2f962a2f1736510f",
  "generated": "2025-02-23T04:45:17.981Z",
  "media": [
    {
      "__outstatic": {
        "commit": "",
        "hash": "0",
        "path": "public/file.svg"
      },
      "alt": "",
      "filename": "file.svg",
      "publishedAt": "2025-02-23T04:44:24.500Z",
      "type": "image"
    },
    {
      "__outstatic": {
        "commit": "",
        "hash": "0",
        "path": "public/globe.svg"
      },
      "alt": "",
      "filename": "globe.svg",
      "publishedAt": "2025-02-23T04:44:24.500Z",
      "type": "image"
    },
    {
      "__outstatic": {
        "commit": "815dd4ece678e9823c89eaaf2f962a2f1736510f",
        "hash": "1001864997",
        "path": "public/image_fx_-E1NT.jpg"
      },
      "alt": "",
      "filename": "image_fx_-E1NT.jpg",
      "publishedAt": "2025-02-23T04:45:17.981Z",
      "type": "image"
    },
    {
      "__outstatic": {
        "commit": "",
        "hash": "0",
        "path": "public/next.svg"
      },
      "alt": "",
      "filename": "next.svg",
      "publishedAt": "2025-02-23T04:44:24.500Z",
      "type": "image"
    },
    {
      "__outstatic": {
        "commit": "",
        "hash": "0",
        "path": "public/vercel.svg"
      },
      "alt": "",
      "filename": "vercel.svg",
      "publishedAt": "2025-02-23T04:44:24.500Z",
      "type": "image"
    },
    {
      "__outstatic": {
        "commit": "",
        "hash": "0",
        "path": "public/window.svg"
      },
      "alt": "",
      "filename": "window.svg",
      "publishedAt": "2025-02-23T04:44:24.500Z",
      "type": "image"
    }
  ]
}